{
    "cluster": "cruddur",
    "launchType": "FARGATE",
    "desiredCount": 1,
    "enableECSManagedTags": true,
    "enableExecuteCommand": true,
    "networkConfiguration": {
      "awsvpcConfiguration": {
        "assignPublicIp": "ENABLED",
        "securityGroups": [
          "sg-0fa7234faed79f5c8"
        ],
        "subnets": [
          "subnet-0dc2943e7b872770f",
          "subnet-0e2ea45605c07ff6e",
          "subnet-0ab4c925a0bd50c42"
        ]
      }
    },
    "propagateTags": "SERVICE",
    "serviceName": "backend-flask",
    "taskDefinition": "backend-flask",
    "serviceConnectConfiguration": {
      "enabled": true,
      "namespace": "cruddur",
      "services": [
        {
          "portName": "backend-flask",
          "discoveryName": "backend-flask",
          "clientAliases": [{"port": 4567}]
        }
      ]
    }
  }